ppf_measures/__init__.py
ppf_measures/hmra_var_tvar.py
ppf_measures/ppf_integral.py
ppf_measures/tail_value_at_risk.py
ppf_measures/value_at_risk.py
ppf_measures-0.1.1.dist-info/licenses/LICENSE
ppf_measures-0.1.1.dist-info/METADATA
ppf_measures-0.1.1.dist-info/WHEEL
ppf_measures-0.1.1.dist-info/top_level.txt
ppf_measures-0.1.1.dist-info/RECORD
