Metadata-Version: 2.4
Name: ppf_measures
Version: 0.1.1
Summary: A library for computing PPF measures
Author: Anitagutzw
License: MIT
Classifier: Programming Language :: Python :: 3
Classifier: License :: OSI Approved :: MIT License
License-File: LICENSE
Requires-Dist: mpmath
Requires-Dist: ppf_approx
Requires-Dist: numpy
Requires-Dist: scipy
Requires-Dist: multires
Dynamic: author
Dynamic: classifier
Dynamic: license
Dynamic: license-file
Dynamic: requires-dist
Dynamic: summary
